[
    {
      "name": "Shreyak Upadhyay",
      "status": "IMT2014049",
      "id": 1
    },
    {
      "name": "Arvind Voggu",
      "status": "IMT2015055",
      "id": 2
    },
    {
      "name": "Biswesh Mahopatra",
      "status": "IMT2016034",
      "id": 3
    },
    {
      "name": "Shivang Arora",
      "status": "IMT2015059",
      "id": 4
    },
    {
      "name": "Atibhi Agarwal",
      "status": "IMT2016048",
      "id": 5
    },
    {
      "name": "Gautami Gupta",
      "status": "IMT2016069",
      "id": 6
    },
    {
      "name": "Amal",
      "status": "MT2017065",
      "id": 7
    }
]